gps_time/__init__.py
gps_time/core.py
gps_time/datetime.py
gps_time/leapseconds.py
gps_time/logutils.py
gps_time/utilities.py
gps_time-3.0.0.dist-info/licenses/LICENSE
gps_time-3.0.0.dist-info/licenses/NOTICE
gps_time-3.0.0.dist-info/METADATA
gps_time-3.0.0.dist-info/WHEEL
gps_time-3.0.0.dist-info/top_level.txt
gps_time-3.0.0.dist-info/RECORD
