Metadata-Version: 2.4
Name: gps_time
Version: 3.0.0
Summary: This module is used to represent GPS time and provide tools for handling it. It is an alternative to the python built-in datetime module that is easier to use for scientific computing.
Author-email: The Aerospace Corporation <david.w.allen@aero.org>
License: Apache-2.0
Keywords: gps,time,python,datetime
Classifier: Development Status :: 5 - Production/Stable
Classifier: Intended Audience :: Science/Research
Classifier: License :: OSI Approved :: Apache Software License
Classifier: Programming Language :: Python :: 3
Requires-Python: >=3.8
License-File: LICENSE
License-File: NOTICE
Requires-Dist: numpy
Requires-Dist: ruamel.yaml
Provides-Extra: dev
Requires-Dist: pytest; extra == "dev"
Requires-Dist: pytest-cov; extra == "dev"
Requires-Dist: black; extra == "dev"
Requires-Dist: flake8; extra == "dev"
Requires-Dist: mkdocs; extra == "dev"
Requires-Dist: mkdocs-material; extra == "dev"
Requires-Dist: mkdocstrings[python]; extra == "dev"
Requires-Dist: genbadge[coverage]; extra == "dev"
Requires-Dist: mkdocs-include-markdown-plugin; extra == "dev"
Dynamic: license-file
